{"trial_id": "0020", "hyperparameters": {"space": [{"class_name": "Int", "config": {"name": "units", "default": null, "conditions": [], "min_value": 8, "max_value": 40, "step": 4, "sampling": "linear"}}, {"class_name": "Choice", "config": {"name": "learning_rate", "default": 0.1, "conditions": [], "values": [0.1, 0.01, 0.001, 0.0001], "ordered": true}}], "values": {"units": 16, "learning_rate": 0.01, "tuner/epochs": 4, "tuner/initial_epoch": 0, "tuner/bracket": 1, "tuner/round": 0}}, "metrics": {"metrics": {"accuracy": {"direction": "max", "observations": [{"value": [0.7108498215675354], "step": 1}]}, "loss": {"direction": "min", "observations": [{"value": [0.5879538059234619], "step": 1}]}, "val_accuracy": {"direction": "max", "observations": [{"value": [0.7191107273101807], "step": 1}]}, "val_loss": {"direction": "min", "observations": [{"value": [0.5864458084106445], "step": 1}]}}}, "score": 0.7191107273101807, "best_step": 1, "status": "COMPLETED", "message": null}